pyqi/__init__.py
pyqi/__main__.py
pyqi_v1-1.1.0.dist-info/METADATA
pyqi_v1-1.1.0.dist-info/WHEEL
pyqi_v1-1.1.0.dist-info/top_level.txt
pyqi_v1-1.1.0.dist-info/RECORD
