Metadata-Version: 2.1
Name: pyqi-v1
Version: 1.1.0
Summary: It can help you quicker install python
Home-page: https://github.com/redish101/pyqi
Author: Redish101
Author-email: jiayunluo@outlook.com
License: UNKNOWN
Project-URL: Bug Tracker, https://github.com/Redish101/pyqi/discussions
Platform: UNKNOWN
Classifier: Programming Language :: Python :: 3
Classifier: License :: OSI Approved :: MIT License
Classifier: Operating System :: OS Independent
Requires-Python: >=3.7
